{
  "contact_information": {
    "phones": {
      "phone": "282 9 756",
      "gsm": "0533-548 3166"
    },
    "addresses": [
      {
        "town": "West",
        "city": "North Kadınana",
        "neighborhood": "West Sidki",
        "name": "Özgün Ayhan Soylu Tevetoğlu",
        "street": "Yaman Via",
        "postal_code": "70678"
      },
      {
        "town": "West",
        "city": "West Ferayeland",
        "neighborhood": "North Mükramin",
        "name": "Tanbay Hançer",
        "street": "Türk Plains",
        "postal_code": "79279"
      },
      {
        "town": "South",
        "city": "Bilirburgh",
        "neighborhood": "Lake Merzukberg",
        "name": "Şahat Şener",
        "street": "Zorlu Tunnel",
        "postal_code": "84695"
      }
    ]
  },
  "lectures": [
    {
      "code": "IND",
      "name": "Et quis nulla et impedit commodi minima.",
      "ects_credit": 3,
      "note": 60,
      "credit": 2,
      "exams": [
        {
          "date": "2015-01-18",
          "points": 52,
          "type": "H"
        },
        {
          "date": "2014-12-29",
          "points": 79,
          "type": "D"
        },
        {
          "date": "2013-12-30",
          "points": 97,
          "type": "D"
        },
        {
          "date": "2014-09-05",
          "points": 69,
          "type": "H"
        },
        {
          "date": "2014-03-04",
          "points": 14,
          "type": "D"
        },
        {
          "date": "2012-07-03",
          "points": 72,
          "type": "E"
        }
      ]
    },
    {
      "code": "LIG",
      "name": "Voluptatem provident soluta sunt blanditiis autem.",
      "ects_credit": 2,
      "note": 2,
      "credit": 5,
      "exams": [
        {
          "date": "2014-01-04",
          "points": 51,
          "type": "H"
        },
        {
          "date": "2014-01-31",
          "points": 93,
          "type": "C"
        },
        {
          "date": "2014-05-19",
          "points": 96,
          "type": "E"
        },
        {
          "date": "2014-12-19",
          "points": 25,
          "type": "A"
        }
      ]
    },
    {
      "code": "LIG",
      "name": "Iusto in at eveniet alias est.",
      "ects_credit": 7,
      "note": 86,
      "credit": 7,
      "exams": [
        {
          "date": "2012-05-10",
          "points": 94,
          "type": "H"
        },
        {
          "date": "2013-10-07",
          "points": 26,
          "type": "H"
        },
        {
          "date": "2014-01-31",
          "points": 12,
          "type": "F"
        }
      ]
    },
    {
      "code": "DEE",
      "name": "Est in autem et.",
      "ects_credit": 1,
      "note": 80,
      "credit": 1,
      "exams": [
        {
          "date": "2013-12-18",
          "points": 7,
          "type": "B"
        },
        {
          "date": "2014-05-26",
          "points": 70,
          "type": "E"
        },
        {
          "date": "2012-05-20",
          "points": 59,
          "type": "G"
        }
      ]
    },
    {
      "code": "AQU",
      "name": "Debitis delectus quia fugiat.",
      "ects_credit": 1,
      "note": 55,
      "credit": 8,
      "exams": [
        {
          "date": "2014-02-23",
          "points": 64,
          "type": "C"
        },
        {
          "date": "2014-02-13",
          "points": 4,
          "type": "C"
        }
      ]
    },
    {
      "code": "POW",
      "name": "Sit qui qui est.",
      "ects_credit": 6,
      "note": 92,
      "credit": 5,
      "exams": [
        {
          "date": "2014-11-23",
          "points": 25,
          "type": "F"
        },
        {
          "date": "2013-10-18",
          "points": 86,
          "type": "A"
        },
        {
          "date": "2011-11-19",
          "points": 31,
          "type": "E"
        },
        {
          "date": "2011-10-05",
          "points": 23,
          "type": "D"
        },
        {
          "date": "2011-07-28",
          "points": 37,
          "type": "E"
        }
      ]
    },
    {
      "code": "DAR",
      "name": "Sequi iusto id sequi expedita sunt.",
      "ects_credit": 2,
      "note": 92,
      "credit": 2,
      "exams": [
        {
          "date": "2012-06-10",
          "points": 54,
          "type": "C"
        },
        {
          "date": "2013-01-09",
          "points": 77,
          "type": "C"
        },
        {
          "date": "2013-03-15",
          "points": 64,
          "type": "H"
        },
        {
          "date": "2015-04-06",
          "points": 20,
          "type": "F"
        },
        {
          "date": "2011-08-04",
          "points": 23,
          "type": "A"
        },
        {
          "date": "2014-11-11",
          "points": 57,
          "type": "A"
        },
        {
          "date": "2012-06-11",
          "points": 100,
          "type": "B"
        },
        {
          "date": "2014-06-25",
          "points": 19,
          "type": "D"
        }
      ]
    },
    {
      "code": "FLO",
      "name": "Temporibus mollitia nisi corrupti consectetur doloribus.",
      "ects_credit": 7,
      "note": 51,
      "credit": 7,
      "exams": [
        {
          "date": "2012-08-16",
          "points": 76,
          "type": "H"
        },
        {
          "date": "2012-05-02",
          "points": 30,
          "type": "H"
        },
        {
          "date": "2015-01-03",
          "points": 47,
          "type": "F"
        },
        {
          "date": "2011-04-27",
          "points": 52,
          "type": "A"
        },
        {
          "date": "2012-01-26",
          "points": 10,
          "type": "F"
        },
        {
          "date": "2011-07-05",
          "points": 29,
          "type": "F"
        }
      ]
    },
    {
      "code": "TOM",
      "name": "Vel esse nihil temporibus.",
      "ects_credit": 3,
      "note": 31,
      "credit": 2,
      "exams": [
        {
          "date": "2012-09-04",
          "points": 71,
          "type": "A"
        },
        {
          "date": "2013-03-29",
          "points": 58,
          "type": "E"
        },
        {
          "date": "2013-10-26",
          "points": 45,
          "type": "H"
        },
        {
          "date": "2014-11-16",
          "points": 65,
          "type": "B"
        },
        {
          "date": "2011-06-12",
          "points": 31,
          "type": "H"
        },
        {
          "date": "2015-04-04",
          "points": 17,
          "type": "E"
        },
        {
          "date": "2014-07-28",
          "points": 68,
          "type": "C"
        },
        {
          "date": "2014-09-04",
          "points": 42,
          "type": "A"
        },
        {
          "date": "2012-03-26",
          "points": 7,
          "type": "D"
        },
        {
          "date": "2014-04-18",
          "points": 41,
          "type": "G"
        }
      ]
    },
    {
      "code": "LIG",
      "name": "Sit sit reprehenderit possimus esse.",
      "ects_credit": 8,
      "note": 9,
      "credit": 6,
      "exams": [
        {
          "date": "2012-06-06",
          "points": 4,
          "type": "H"
        },
        {
          "date": "2015-01-03",
          "points": 73,
          "type": "E"
        },
        {
          "date": "2012-02-03",
          "points": 4,
          "type": "G"
        },
        {
          "date": "2012-12-08",
          "points": 40,
          "type": "A"
        },
        {
          "date": "2011-04-16",
          "points": 18,
          "type": "E"
        },
        {
          "date": "2012-07-07",
          "points": 9,
          "type": "F"
        },
        {
          "date": "2014-02-04",
          "points": 18,
          "type": "A"
        }
      ]
    },
    {
      "code": "BLA",
      "name": "Cupiditate nostrum consequatur harum.",
      "ects_credit": 4,
      "note": 17,
      "credit": 3,
      "exams": [
        {
          "date": "2011-11-01",
          "points": 57,
          "type": "D"
        },
        {
          "date": "2013-02-20",
          "points": 24,
          "type": "A"
        },
        {
          "date": "2013-02-17",
          "points": 80,
          "type": "G"
        },
        {
          "date": "2012-11-05",
          "points": 92,
          "type": "B"
        },
        {
          "date": "2014-05-16",
          "points": 83,
          "type": "G"
        },
        {
          "date": "2013-10-04",
          "points": 98,
          "type": "H"
        },
        {
          "date": "2012-02-17",
          "points": 54,
          "type": "A"
        },
        {
          "date": "2012-06-27",
          "points": 53,
          "type": "D"
        },
        {
          "date": "2013-01-02",
          "points": 56,
          "type": "G"
        }
      ]
    },
    {
      "code": "FUC",
      "name": "Consectetur sed et cum sit.",
      "ects_credit": 8,
      "note": 57,
      "credit": 6,
      "exams": [
        {
          "date": "2013-03-05",
          "points": 80,
          "type": "D"
        },
        {
          "date": "2014-02-05",
          "points": 71,
          "type": "E"
        },
        {
          "date": "2014-02-20",
          "points": 70,
          "type": "H"
        },
        {
          "date": "2014-10-25",
          "points": 52,
          "type": "H"
        },
        {
          "date": "2011-06-24",
          "points": 11,
          "type": "B"
        }
      ]
    },
    {
      "code": "BEI",
      "name": "Saepe nemo aperiam quo sequi et fuga.",
      "ects_credit": 7,
      "note": 34,
      "credit": 8,
      "exams": [
        {
          "date": "2012-05-15",
          "points": 31,
          "type": "C"
        },
        {
          "date": "2011-05-25",
          "points": 35,
          "type": "D"
        }
      ]
    },
    {
      "code": "BLU",
      "name": "Eum nam amet dolorum quaerat.",
      "ects_credit": 4,
      "note": 51,
      "credit": 7,
      "exams": [
        {
          "date": "2014-05-13",
          "points": 1,
          "type": "G"
        }
      ]
    },
    {
      "code": "WHE",
      "name": "Corrupti at corporis consequatur dolor alias.",
      "ects_credit": 3,
      "note": 61,
      "credit": 8,
      "exams": [
        {
          "date": "2013-06-23",
          "points": 69,
          "type": "F"
        },
        {
          "date": "2011-04-12",
          "points": 50,
          "type": "E"
        },
        {
          "date": "2013-01-21",
          "points": 46,
          "type": "F"
        }
      ]
    },
    {
      "code": "SAL",
      "name": "Odio quia quidem voluptas quis distinctio sed.",
      "ects_credit": 6,
      "note": 11,
      "credit": 5,
      "exams": [
        {
          "date": "2012-01-28",
          "points": 1,
          "type": "D"
        },
        {
          "date": "2014-10-20",
          "points": 48,
          "type": "F"
        },
        {
          "date": "2011-08-22",
          "points": 53,
          "type": "B"
        },
        {
          "date": "2013-12-05",
          "points": 7,
          "type": "H"
        },
        {
          "date": "2012-12-08",
          "points": 15,
          "type": "B"
        },
        {
          "date": "2011-04-22",
          "points": 37,
          "type": "H"
        },
        {
          "date": "2014-06-30",
          "points": 57,
          "type": "C"
        },
        {
          "date": "2012-02-28",
          "points": 61,
          "type": "D"
        }
      ]
    },
    {
      "code": "SEA",
      "name": "Ab dolores ut nesciunt dolores.",
      "ects_credit": 4,
      "note": 30,
      "credit": 2,
      "exams": [
        {
          "date": "2014-12-13",
          "points": 48,
          "type": "G"
        },
        {
          "date": "2014-08-17",
          "points": 79,
          "type": "G"
        },
        {
          "date": "2013-04-24",
          "points": 37,
          "type": "E"
        },
        {
          "date": "2011-12-14",
          "points": 22,
          "type": "A"
        },
        {
          "date": "2012-06-27",
          "points": 60,
          "type": "A"
        },
        {
          "date": "2013-09-20",
          "points": 27,
          "type": "A"
        },
        {
          "date": "2012-04-16",
          "points": 54,
          "type": "D"
        },
        {
          "date": "2014-06-04",
          "points": 5,
          "type": "C"
        },
        {
          "date": "2012-05-31",
          "points": 22,
          "type": "F"
        },
        {
          "date": "2011-05-08",
          "points": 16,
          "type": "A"
        }
      ]
    },
    {
      "code": "ORA",
      "name": "Quia laudantium et est optio.",
      "ects_credit": 1,
      "note": 2,
      "credit": 6,
      "exams": [
        {
          "date": "2013-09-07",
          "points": 8,
          "type": "G"
        },
        {
          "date": "2012-03-14",
          "points": 53,
          "type": "A"
        },
        {
          "date": "2015-01-22",
          "points": 83,
          "type": "D"
        },
        {
          "date": "2013-01-03",
          "points": 19,
          "type": "E"
        },
        {
          "date": "2014-04-04",
          "points": 74,
          "type": "D"
        },
        {
          "date": "2011-04-15",
          "points": 15,
          "type": "H"
        },
        {
          "date": "2012-11-30",
          "points": 92,
          "type": "F"
        },
        {
          "date": "2012-06-09",
          "points": 100,
          "type": "F"
        },
        {
          "date": "2015-03-23",
          "points": 85,
          "type": "G"
        },
        {
          "date": "2013-09-22",
          "points": 58,
          "type": "F"
        }
      ]
    },
    {
      "code": "SAN",
      "name": "Porro est eaque sit.",
      "ects_credit": 1,
      "note": 19,
      "credit": 7,
      "exams": [
        {
          "date": "2012-05-23",
          "points": 4,
          "type": "G"
        },
        {
          "date": "2014-01-12",
          "points": 100,
          "type": "F"
        },
        {
          "date": "2013-01-02",
          "points": 51,
          "type": "F"
        },
        {
          "date": "2013-11-29",
          "points": 64,
          "type": "C"
        },
        {
          "date": "2012-10-25",
          "points": 30,
          "type": "H"
        },
        {
          "date": "2013-03-06",
          "points": 9,
          "type": "F"
        },
        {
          "date": "2013-02-14",
          "points": 31,
          "type": "H"
        },
        {
          "date": "2013-11-24",
          "points": 83,
          "type": "C"
        }
      ]
    },
    {
      "code": "OLI",
      "name": "Velit doloremque repellendus quam nihil laborum atque.",
      "ects_credit": 8,
      "note": 28,
      "credit": 3,
      "exams": [
        {
          "date": "2012-07-03",
          "points": 63,
          "type": "F"
        },
        {
          "date": "2011-11-01",
          "points": 40,
          "type": "E"
        },
        {
          "date": "2014-10-02",
          "points": 50,
          "type": "F"
        },
        {
          "date": "2014-11-05",
          "points": 15,
          "type": "E"
        },
        {
          "date": "2012-11-11",
          "points": 8,
          "type": "G"
        }
      ]
    },
    {
      "code": "NAV",
      "name": "Ut ipsa iure sed.",
      "ects_credit": 6,
      "note": 98,
      "credit": 5,
      "exams": [
        {
          "date": "2013-07-01",
          "points": 2,
          "type": "E"
        },
        {
          "date": "2011-11-27",
          "points": 68,
          "type": "H"
        }
      ]
    },
    {
      "code": "MED",
      "name": "Autem laborum architecto et dolor.",
      "ects_credit": 3,
      "note": 2,
      "credit": 6,
      "exams": [
        {
          "date": "2014-03-05",
          "points": 81,
          "type": "G"
        },
        {
          "date": "2014-02-24",
          "points": 5,
          "type": "D"
        },
        {
          "date": "2014-07-27",
          "points": 65,
          "type": "C"
        },
        {
          "date": "2011-09-12",
          "points": 24,
          "type": "E"
        },
        {
          "date": "2011-05-24",
          "points": 56,
          "type": "H"
        },
        {
          "date": "2014-06-25",
          "points": 6,
          "type": "E"
        },
        {
          "date": "2011-07-13",
          "points": 13,
          "type": "H"
        },
        {
          "date": "2012-11-16",
          "points": 27,
          "type": "H"
        },
        {
          "date": "2013-09-25",
          "points": 74,
          "type": "A"
        }
      ]
    },
    {
      "code": "SLA",
      "name": "Maiores doloremque praesentium sunt.",
      "ects_credit": 2,
      "note": 89,
      "credit": 5,
      "exams": [
        {
          "date": "2014-11-05",
          "points": 65,
          "type": "D"
        },
        {
          "date": "2013-08-02",
          "points": 41,
          "type": "H"
        },
        {
          "date": "2013-05-25",
          "points": 98,
          "type": "H"
        },
        {
          "date": "2011-11-03",
          "points": 36,
          "type": "A"
        },
        {
          "date": "2013-04-07",
          "points": 18,
          "type": "H"
        }
      ]
    },
    {
      "code": "PAL",
      "name": "Totam commodi occaecati ea a.",
      "ects_credit": 5,
      "note": 90,
      "credit": 2,
      "exams": [
        {
          "date": "2012-12-30",
          "points": 43,
          "type": "G"
        },
        {
          "date": "2011-05-06",
          "points": 43,
          "type": "D"
        },
        {
          "date": "2012-11-01",
          "points": 98,
          "type": "D"
        },
        {
          "date": "2013-04-01",
          "points": 50,
          "type": "H"
        },
        {
          "date": "2012-01-22",
          "points": 40,
          "type": "G"
        },
        {
          "date": "2012-07-15",
          "points": 65,
          "type": "G"
        },
        {
          "date": "2013-12-21",
          "points": 14,
          "type": "F"
        },
        {
          "date": "2012-11-03",
          "points": 59,
          "type": "H"
        },
        {
          "date": "2013-09-29",
          "points": 54,
          "type": "F"
        }
      ]
    },
    {
      "code": "DOD",
      "name": "Quaerat adipisci vel doloremque ab tempora omnis.",
      "ects_credit": 2,
      "note": 43,
      "credit": 7,
      "exams": [
        {
          "date": "2011-10-02",
          "points": 70,
          "type": "H"
        },
        {
          "date": "2013-05-23",
          "points": 39,
          "type": "H"
        },
        {
          "date": "2013-09-12",
          "points": 58,
          "type": "H"
        },
        {
          "date": "2012-12-15",
          "points": 95,
          "type": "B"
        },
        {
          "date": "2012-01-15",
          "points": 30,
          "type": "B"
        },
        {
          "date": "2014-04-05",
          "points": 52,
          "type": "B"
        }
      ]
    },
    {
      "code": "LAV",
      "name": "Sunt omnis recusandae ea sint suscipit.",
      "ects_credit": 2,
      "note": 28,
      "credit": 5,
      "exams": [
        {
          "date": "2013-02-26",
          "points": 97,
          "type": "G"
        },
        {
          "date": "2012-08-24",
          "points": 73,
          "type": "G"
        },
        {
          "date": "2014-06-14",
          "points": 1,
          "type": "F"
        },
        {
          "date": "2013-06-23",
          "points": 12,
          "type": "B"
        },
        {
          "date": "2012-05-16",
          "points": 25,
          "type": "E"
        },
        {
          "date": "2013-06-26",
          "points": 73,
          "type": "D"
        },
        {
          "date": "2013-11-28",
          "points": 55,
          "type": "B"
        },
        {
          "date": "2011-05-13",
          "points": 49,
          "type": "F"
        },
        {
          "date": "2011-08-15",
          "points": 89,
          "type": "E"
        }
      ]
    },
    {
      "code": "LIG",
      "name": "Culpa quo sit doloribus aperiam.",
      "ects_credit": 3,
      "note": 43,
      "credit": 5,
      "exams": [
        {
          "date": "2015-01-01",
          "points": 78,
          "type": "B"
        },
        {
          "date": "2015-01-07",
          "points": 96,
          "type": "F"
        },
        {
          "date": "2012-03-24",
          "points": 33,
          "type": "D"
        }
      ]
    },
    {
      "code": "DAR",
      "name": "Adipisci qui cum ipsum repellat.",
      "ects_credit": 6,
      "note": 84,
      "credit": 2,
      "exams": [
        {
          "date": "2014-09-19",
          "points": 65,
          "type": "H"
        },
        {
          "date": "2014-06-10",
          "points": 39,
          "type": "F"
        },
        {
          "date": "2013-06-16",
          "points": 30,
          "type": "A"
        },
        {
          "date": "2014-10-28",
          "points": 19,
          "type": "F"
        }
      ]
    },
    {
      "code": "TEA",
      "name": "Quasi quibusdam earum minus.",
      "ects_credit": 3,
      "note": 15,
      "credit": 3,
      "exams": [
        {
          "date": "2012-08-27",
          "points": 58,
          "type": "C"
        },
        {
          "date": "2014-05-01",
          "points": 11,
          "type": "A"
        },
        {
          "date": "2012-03-11",
          "points": 89,
          "type": "F"
        },
        {
          "date": "2014-11-11",
          "points": 19,
          "type": "H"
        },
        {
          "date": "2014-09-02",
          "points": 40,
          "type": "C"
        },
        {
          "date": "2013-03-13",
          "points": 42,
          "type": "G"
        },
        {
          "date": "2011-07-26",
          "points": 43,
          "type": "E"
        }
      ]
    }
  ],
  "join_date": "1997-05-28",
  "student_number": "2811913640768",
  "scholarship": {"active_term": 6},
  "identity_information": {
    "last_name": "Hayrioğlu",
    "neighborhood": "North",
    "family_order": "655",
    "name_of_father": "Rıfkıye",
    "id_card_no": "21448",
    "id_card_serial": "s69",
    "name_of_mother": "Nalân",
    "town": "İlbekborough",
    "city": "North Ümmahan",
    "first_name": "Ceyhun",
    "tc_no": "19169789841",
    "date_of_birth": "1987-06-27",
    "place_of_birth": "Kayagünland",
    "logbook": "802",
    "order": "6803"
  },
  "payment_information": {
    "iban": "PY35668931721894450718818804",
    "fees": {
      "paids": {"date": "2015-04-08T08:06:34"},
      "unpaids": {"last_pay_date": "2015-04-08T08:07:11"},
      "charge_backs": {"date": "2015-04-08T08:08:37"}
    }
  },
  "auth_information": {
    "username": "hayrioglu.iklim",
    "password_reset": {
      "date": "2015-04-08T08:06:12",
      "token": "5472b848a4a97f7dbce153e6a208409ba31385744b1bf8b99ddfb123053bdf06",
      "request_ip": "24.209.51.245",
      "client": "Mozilla/5.0 (iPod; U; CPU iPhone OS 3_3 like Mac OS X; it-IT) AppleWebKit/531.19.3 (KHTML, like Gecko) Version/4.0.5 Mobile/8B113 Safari/6531.19.3"
    },
    "last_login_ip": "160.95.123.220",
    "password_last_changed_date": "2015-04-08T08:06:19",
    "last_login": "2015-04-08T08:09:23",
    "password": "f21573630fc3fc06e4a07451c543aad6b303728d3f6ee35fe2d11c87cfea1673",
    "email": "turk.birsan@frat.net"
  }
}